{
  "owners": [
    { "name": "Kyle Williams", "picks": ["GEV", "VRT", "CEG"] },
    { "name": "John Atkins",   "picks": ["RKLB", "OKLO", "HOOD"] },
    { "name": "Keegan Ball",   "picks": ["NNE", "OKLO", "LUNR"] },
    { "name": "Andrew Fahey",  "picks": ["MU", "STX", "SNDK"], "champion": "Reigning league champion" },
    { "name": "Ryan Sheekley", "picks": ["MU", "AMD", "AVGO"] },
    { "name": "Shawn Henderson", "picks": ["TSLA", "MSTR", "COIN"] },
    { "name": "Karlis Draulis", "picks": ["TSLA", "SPCX", "EBAY"] }
  ]
}
