{
  "generated_utc": "2026-07-01T21:46:52Z",
  "state": "live",
  "standings": [
    {
      "name": "Shawn Henderson",
      "rank": 1,
      "avg": 5.19,
      "points_behind": 0.0,
      "movement": 0,
      "is_new": true,
      "pending": false,
      "champion": null,
      "picks": [
        {
          "sym": "TSLA",
          "name": "Tesla",
          "sector": "Electric Vehicles",
          "pct": 0.88,
          "contribution": 0.29,
          "price": 425.3,
          "day_change_pct": 1.12,
          "baseline": 421.57,
          "spark": {
            "points": "2.0,18.0 62.0,2.0",
            "up": true
          }
        },
        {
          "sym": "MSTR",
          "name": "Strategy (MicroStrategy)",
          "sector": "Bitcoin Treasury",
          "pct": 6.46,
          "contribution": 2.15,
          "price": 93.39,
          "day_change_pct": 7.43,
          "baseline": 87.725,
          "spark": {
            "points": "2.0,18.0 62.0,2.0",
            "up": true
          }
        },
        {
          "sym": "COIN",
          "name": "Coinbase",
          "sector": "Crypto Exchange",
          "pct": 8.23,
          "contribution": 2.74,
          "price": 159.24,
          "day_change_pct": 8.93,
          "baseline": 147.13,
          "spark": {
            "points": "2.0,18.0 62.0,2.0",
            "up": true
          }
        }
      ]
    },
    {
      "name": "John Atkins",
      "rank": 2,
      "avg": 1.45,
      "points_behind": 3.74,
      "movement": 0,
      "is_new": true,
      "pending": false,
      "champion": null,
      "picks": [
        {
          "sym": "RKLB",
          "name": "Rocket Lab",
          "sector": "Space & Aerospace",
          "pct": -1.11,
          "contribution": -0.37,
          "price": 100.07,
          "day_change_pct": -1.55,
          "baseline": 101.195,
          "spark": {
            "points": "2.0,2.0 62.0,18.0",
            "up": false
          }
        },
        {
          "sym": "OKLO",
          "name": "Oklo",
          "sector": "Nuclear Energy",
          "pct": -2.2,
          "contribution": -0.73,
          "price": 52.45,
          "day_change_pct": 0.23,
          "baseline": 53.63,
          "spark": {
            "points": "2.0,2.0 62.0,18.0",
            "up": false
          }
        },
        {
          "sym": "HOOD",
          "name": "Robinhood Markets",
          "sector": "Fintech",
          "pct": 7.67,
          "contribution": 2.56,
          "price": 108.65,
          "day_change_pct": 8.35,
          "baseline": 100.91,
          "spark": {
            "points": "2.0,18.0 62.0,2.0",
            "up": true
          }
        }
      ]
    },
    {
      "name": "Brad Bone",
      "rank": 3,
      "avg": 0.71,
      "points_behind": 4.48,
      "movement": 0,
      "is_new": true,
      "pending": false,
      "champion": null,
      "picks": [
        {
          "sym": "MSFT",
          "name": "Microsoft",
          "sector": "Software & Cloud",
          "pct": 0.91,
          "contribution": 0.3,
          "price": 384.28,
          "day_change_pct": 3.02,
          "baseline": 380.825,
          "spark": {
            "points": "2.0,18.0 62.0,2.0",
            "up": true
          }
        },
        {
          "sym": "ZS",
          "name": "Zscaler",
          "sector": "Cybersecurity",
          "pct": 1.53,
          "contribution": 0.51,
          "price": 146.45,
          "day_change_pct": 3.75,
          "baseline": 144.25,
          "spark": {
            "points": "2.0,18.0 62.0,2.0",
            "up": true
          }
        },
        {
          "sym": "CRWD",
          "name": "CrowdStrike",
          "sector": "Cybersecurity",
          "pct": -0.29,
          "contribution": -0.1,
          "price": 772.74,
          "day_change_pct": 10.22,
          "baseline": 775.0,
          "spark": {
            "points": "2.0,2.0 62.0,18.0",
            "up": false
          }
        }
      ]
    },
    {
      "name": "Andrew Fahey",
      "rank": 4,
      "avg": -1.76,
      "points_behind": 6.95,
      "movement": 0,
      "is_new": true,
      "pending": false,
      "champion": "Reigning league champion",
      "picks": [
        {
          "sym": "MU",
          "name": "Micron Technology",
          "sector": "Semiconductors",
          "pct": -4.6,
          "contribution": -1.53,
          "price": 1032.28,
          "day_change_pct": -10.57,
          "baseline": 1082.08,
          "spark": {
            "points": "2.0,2.0 62.0,18.0",
            "up": false
          }
        },
        {
          "sym": "STX",
          "name": "Seagate Technology",
          "sector": "Data Storage",
          "pct": 1.85,
          "contribution": 0.62,
          "price": 915.19,
          "day_change_pct": -5.16,
          "baseline": 898.55,
          "spark": {
            "points": "2.0,18.0 62.0,2.0",
            "up": true
          }
        },
        {
          "sym": "SNDK",
          "name": "Sandisk",
          "sector": "Data Storage",
          "pct": -2.54,
          "contribution": -0.85,
          "price": 2032.22,
          "day_change_pct": -10.62,
          "baseline": 2085.1699,
          "spark": {
            "points": "2.0,2.0 62.0,18.0",
            "up": false
          }
        }
      ]
    },
    {
      "name": "John Pappas",
      "rank": 5,
      "avg": -2.43,
      "points_behind": 7.62,
      "movement": 0,
      "is_new": true,
      "pending": false,
      "champion": null,
      "picks": [
        {
          "sym": "ETN",
          "name": "Eaton",
          "sector": "Power Management",
          "pct": -1.83,
          "contribution": -0.61,
          "price": 412.31,
          "day_change_pct": -3.24,
          "baseline": 419.99,
          "spark": {
            "points": "2.0,2.0 62.0,18.0",
            "up": false
          }
        },
        {
          "sym": "VRT",
          "name": "Vertiv Holdings",
          "sector": "Data-Center Infrastructure",
          "pct": -4.41,
          "contribution": -1.47,
          "price": 311.42,
          "day_change_pct": -6.99,
          "baseline": 325.8,
          "spark": {
            "points": "2.0,2.0 62.0,18.0",
            "up": false
          }
        },
        {
          "sym": "GEV",
          "name": "GE Vernova",
          "sector": "Power & Electrification",
          "pct": -1.05,
          "contribution": -0.35,
          "price": 1134.35,
          "day_change_pct": -3.45,
          "baseline": 1146.4,
          "spark": {
            "points": "2.0,2.0 62.0,18.0",
            "up": false
          }
        }
      ]
    },
    {
      "name": "Karlis Draulis",
      "rank": 6,
      "avg": -2.57,
      "points_behind": 7.76,
      "movement": 0,
      "is_new": true,
      "pending": false,
      "champion": null,
      "picks": [
        {
          "sym": "TSLA",
          "name": "Tesla",
          "sector": "Electric Vehicles",
          "pct": 0.88,
          "contribution": 0.29,
          "price": 425.3,
          "day_change_pct": 1.12,
          "baseline": 421.57,
          "spark": {
            "points": "2.0,18.0 62.0,2.0",
            "up": true
          }
        },
        {
          "sym": "SPCX",
          "name": "SpaceX",
          "sector": "Space & Aerospace",
          "pct": -8.17,
          "contribution": -2.72,
          "price": 157.54,
          "day_change_pct": -7.8,
          "baseline": 171.565,
          "spark": {
            "points": "2.0,2.0 62.0,18.0",
            "up": false
          }
        },
        {
          "sym": "EBAY",
          "name": "eBay",
          "sector": "E-Commerce",
          "pct": -0.42,
          "contribution": -0.14,
          "price": 111.28,
          "day_change_pct": -0.42,
          "baseline": 111.75,
          "spark": {
            "points": "2.0,2.0 62.0,18.0",
            "up": false
          }
        }
      ]
    },
    {
      "name": "Ryan Sheekley",
      "rank": 7,
      "avg": -2.75,
      "points_behind": 7.94,
      "movement": 0,
      "is_new": true,
      "pending": false,
      "champion": null,
      "picks": [
        {
          "sym": "MU",
          "name": "Micron Technology",
          "sector": "Semiconductors",
          "pct": -4.6,
          "contribution": -1.53,
          "price": 1032.28,
          "day_change_pct": -10.57,
          "baseline": 1082.08,
          "spark": {
            "points": "2.0,2.0 62.0,18.0",
            "up": false
          }
        },
        {
          "sym": "AMD",
          "name": "Advanced Micro Devices",
          "sector": "Semiconductors",
          "pct": -2.99,
          "contribution": -1.0,
          "price": 540.88,
          "day_change_pct": -6.89,
          "baseline": 557.53,
          "spark": {
            "points": "2.0,2.0 62.0,18.0",
            "up": false
          }
        },
        {
          "sym": "AVGO",
          "name": "Broadcom",
          "sector": "Semiconductors",
          "pct": -0.66,
          "contribution": -0.22,
          "price": 369.34,
          "day_change_pct": -2.23,
          "baseline": 371.79,
          "spark": {
            "points": "2.0,2.0 62.0,18.0",
            "up": false
          }
        }
      ]
    },
    {
      "name": "Luke Clark",
      "rank": 8,
      "avg": -2.82,
      "points_behind": 8.01,
      "movement": 0,
      "is_new": true,
      "pending": false,
      "champion": null,
      "picks": [
        {
          "sym": "MARA",
          "name": "MARA Holdings",
          "sector": "Bitcoin Mining",
          "pct": -3.26,
          "contribution": -1.09,
          "price": 13.37,
          "day_change_pct": -3.74,
          "baseline": 13.82,
          "spark": {
            "points": "2.0,2.0 62.0,18.0",
            "up": false
          }
        },
        {
          "sym": "IOVA",
          "name": "Iovance Biotherapeutics",
          "sector": "Biotech",
          "pct": -4.57,
          "contribution": -1.52,
          "price": 3.97,
          "day_change_pct": -4.57,
          "baseline": 4.16,
          "spark": {
            "points": "2.0,2.0 62.0,18.0",
            "up": false
          }
        },
        {
          "sym": "RZLV",
          "name": "Rezolve AI",
          "sector": "AI Software",
          "pct": -0.65,
          "contribution": -0.22,
          "price": 3.08,
          "day_change_pct": -2.22,
          "baseline": 3.1,
          "spark": {
            "points": "2.0,2.0 62.0,18.0",
            "up": false
          }
        }
      ]
    },
    {
      "name": "Kyle Williams",
      "rank": 9,
      "avg": -3.22,
      "points_behind": 8.41,
      "movement": 0,
      "is_new": true,
      "pending": false,
      "champion": null,
      "picks": [
        {
          "sym": "GEV",
          "name": "GE Vernova",
          "sector": "Power & Electrification",
          "pct": -1.05,
          "contribution": -0.35,
          "price": 1134.35,
          "day_change_pct": -3.45,
          "baseline": 1146.4,
          "spark": {
            "points": "2.0,2.0 62.0,18.0",
            "up": false
          }
        },
        {
          "sym": "VRT",
          "name": "Vertiv Holdings",
          "sector": "Data-Center Infrastructure",
          "pct": -4.41,
          "contribution": -1.47,
          "price": 311.42,
          "day_change_pct": -6.99,
          "baseline": 325.8,
          "spark": {
            "points": "2.0,2.0 62.0,18.0",
            "up": false
          }
        },
        {
          "sym": "CEG",
          "name": "Constellation Energy",
          "sector": "Nuclear Utilities",
          "pct": -4.2,
          "contribution": -1.4,
          "price": 236.5,
          "day_change_pct": -4.78,
          "baseline": 246.87,
          "spark": {
            "points": "2.0,2.0 62.0,18.0",
            "up": false
          }
        }
      ]
    },
    {
      "name": "Keegan Ball",
      "rank": 10,
      "avg": -3.9,
      "points_behind": 9.09,
      "movement": 0,
      "is_new": true,
      "pending": false,
      "champion": null,
      "picks": [
        {
          "sym": "NNE",
          "name": "Nano Nuclear Energy",
          "sector": "Nuclear Energy",
          "pct": -1.89,
          "contribution": -0.63,
          "price": 20.75,
          "day_change_pct": -1.84,
          "baseline": 21.15,
          "spark": {
            "points": "2.0,2.0 62.0,18.0",
            "up": false
          }
        },
        {
          "sym": "OKLO",
          "name": "Oklo",
          "sector": "Nuclear Energy",
          "pct": -2.2,
          "contribution": -0.73,
          "price": 52.45,
          "day_change_pct": 0.23,
          "baseline": 53.63,
          "spark": {
            "points": "2.0,2.0 62.0,18.0",
            "up": false
          }
        },
        {
          "sym": "LUNR",
          "name": "Intuitive Machines",
          "sector": "Space & Aerospace",
          "pct": -7.61,
          "contribution": -2.54,
          "price": 20.2,
          "day_change_pct": -5.56,
          "baseline": 21.865,
          "spark": {
            "points": "2.0,2.0 62.0,18.0",
            "up": false
          }
        }
      ]
    }
  ]
}
